egsnrc/__init__.py
egsnrc-0.1.0.dist-info/WHEEL
egsnrc-0.1.0.dist-info/METADATA
egsnrc-0.1.0.dist-info/RECORD
